[
    {
      "path": "/images/africa/image1.jpg",
      "alt": "Africa 1"
    },
    {
      "path": "/images/africa/image2.jpg",
      "alt": "Africa 2"
    },
    {
      "path": "/images/africa/image3.jpg",
      "alt": "Africa 3"
    },
    {
      "path": "/images/africa/image4.jpg",
      "alt": "Africa 4"
    },
    {
      "path": "/images/africa/image5.jpg",
      "alt": "Africa 5"
    },
    {
      "path": "/images/africa/image6.jpg",
      "alt": "Africa 6"
    },
    {
      "path": "/images/africa/image7.jpg",
      "alt": "Africa 7"
    },
    {
      "path": "/images/africa/image8.jpg",
      "alt": "Africa 8"
    },
    {
      "path": "/images/africa/image9.jpg",
      "alt": "Africa 9"
    },
    {
      "path": "/images/africa/image10.jpg",
      "alt": "Africa 10"
    },
    {
      "path": "/images/africa/image11.jpg",
      "alt": "Africa 11"
    },
    {
      "path": "/images/africa/image12.jpg",
      "alt": "Africa 12"
    },
    {
      "path": "/images/africa/image13.jpg",
      "alt": "Africa 13"
    },
    {
      "path": "/images/africa/image14.jpg",
      "alt": "Africa 14"
    }
  ]
  